egr_314_esp32_mqtt/__init__.py
egr_314_esp32_mqtt/test.py
egr_314_esp32_mqtt-0.0.1.dist-info/METADATA
egr_314_esp32_mqtt-0.0.1.dist-info/WHEEL
egr_314_esp32_mqtt-0.0.1.dist-info/top_level.txt
egr_314_esp32_mqtt-0.0.1.dist-info/RECORD
