Metadata-Version: 2.1
Name: egr-314-esp32-mqtt
Version: 0.0.1
Summary: This is a package for connecting to mqtt servers
Home-page: https://github.com/embedded-systems-design/code_esp32_mqtt
Author: Dan Aukes
Author-email: danaukes@gmail.com
License: MIT
Platform: UNKNOWN
Classifier: Programming Language :: Python
Classifier: Programming Language :: Python :: 3
